dante/__init__.py
dante/__main__.py
dante/api.py
dante/cli.py
dante/config.py
dante/messages.py
dante/version.py
dante/commands/__init__.py
dante/commands/check.py
dante/commands/config.py
dante/commands/conflicts.py
dante/commands/cyclic.py
dante/commands/graph.py
dante/commands/list.py
dante/commands/lock.py
dante/commands/missing_requirements.py
dante/commands/tree.py
dante/commands/utils.py
dante/commands/validate.py
dante/core/__init__.py
dante/core/color.py
dante/core/graph.py
dante/core/models.py
dante/core/operations.py
dante/core/printer.py
dante/parsers/__init__.py
dante/parsers/base.py
dante/parsers/pip.py
dante/vendor/__init__.py
dante/vendor/appdirs/__init__.py
dante/vendor/appdirs/appdirs.py
dante/vendor/colorama/__init__.py
dante/vendor/colorama/ansi.py
dante/vendor/colorama/ansitowin32.py
dante/vendor/colorama/initialise.py
dante/vendor/colorama/win32.py
dante/vendor/colorama/winterm.py
dante/vendor/graphviz/__init__.py
dante/vendor/graphviz/_compat.py
dante/vendor/graphviz/backend.py
dante/vendor/graphviz/dot.py
dante/vendor/graphviz/files.py
dante/vendor/graphviz/lang.py
dante/vendor/graphviz/tools.py
dante/vendor/packaging/__about__.py
dante/vendor/packaging/__init__.py
dante/vendor/packaging/_compat.py
dante/vendor/packaging/_structures.py
dante/vendor/packaging/markers.py
dante/vendor/packaging/requirements.py
dante/vendor/packaging/specifiers.py
dante/vendor/packaging/utils.py
dante/vendor/packaging/version.py
dante/vendor/pkg_resources/__init__.py
dante/vendor/pkg_resources/py31compat.py
dante/vendor/pyparsing/__init__.py
dante/vendor/pyparsing/pyparsing.py
dante/vendor/six/__init__.py
dante/vendor/six/six.py
dante-2.0.5.dist-info/LICENSE
dante-2.0.5.dist-info/METADATA
dante-2.0.5.dist-info/WHEEL
dante-2.0.5.dist-info/entry_points.txt
dante-2.0.5.dist-info/top_level.txt
dante-2.0.5.dist-info/RECORD
