Metadata-Version: 2.1
Name: dante
Version: 2.0.5
Summary: Python dependency management utility
Home-page: https://github.com/sbg/dante
Maintainer: Seven Bridges Genomics Inc.
Maintainer-email: quicksilver.machine@gmail.com
License: Apache Software License 2.0
Keywords: lock,dependency,pip,requirement,sbg,sevenbridges
Platform: Windows
Platform: POSIX
Platform: MacOs
Classifier: License :: OSI Approved :: Apache Software License
Classifier: Operating System :: OS Independent
Classifier: Programming Language :: Python
Classifier: Programming Language :: Python :: 3
Classifier: Topic :: Software Development
Classifier: Topic :: Software Development :: Libraries :: Python Modules
